odoo/addons/calendar_import_ics/README.rst
odoo/addons/calendar_import_ics/__init__.py
odoo/addons/calendar_import_ics/__manifest__.py
odoo/addons/calendar_import_ics/i18n/calendar_import_ics.pot
odoo/addons/calendar_import_ics/i18n/it.po
odoo/addons/calendar_import_ics/models/__init__.py
odoo/addons/calendar_import_ics/models/calendar_event.py
odoo/addons/calendar_import_ics/readme/CONTRIBUTORS.md
odoo/addons/calendar_import_ics/readme/DESCRIPTION.md
odoo/addons/calendar_import_ics/readme/USAGE.md
odoo/addons/calendar_import_ics/security/calendar_import_security.xml
odoo/addons/calendar_import_ics/security/ir.model.access.csv
odoo/addons/calendar_import_ics/static/description/icon.png
odoo/addons/calendar_import_ics/static/description/index.html
odoo/addons/calendar_import_ics/tests/__init__.py
odoo/addons/calendar_import_ics/tests/test_calendar_import_ics.py
odoo/addons/calendar_import_ics/tests/sample_files/test_calendar.ics
odoo/addons/calendar_import_ics/tests/sample_files/test_calendar_2.ics
odoo/addons/calendar_import_ics/tests/sample_files/test_calendar_3.ics
odoo/addons/calendar_import_ics/wizards/__init__.py
odoo/addons/calendar_import_ics/wizards/wizard_import_ics.py
odoo/addons/calendar_import_ics/wizards/wizard_import_ics.xml
odoo_addon_calendar_import_ics-18.0.1.0.1.4.dist-info/METADATA
odoo_addon_calendar_import_ics-18.0.1.0.1.4.dist-info/WHEEL
odoo_addon_calendar_import_ics-18.0.1.0.1.4.dist-info/top_level.txt
odoo_addon_calendar_import_ics-18.0.1.0.1.4.dist-info/RECORD
